{
    "remotePath": "/public_html/",
    "host": "147.93.92.123",
    "username": "u456104939.lockmebox.com",
    "password": "A[W7pSoJ(?hBp+FJ/i{UgX2>Oj87ZZ~xwCFF|x",
    "port": "21",
    "protocol": "ftp",
    "secure": false,
    "uploadOnSave": false,
    "passive": false,
    "debug": false,
    "privateKeyPath": null,
    "passphrase": null,
    "agent": null,
    "allow": [],
    "ignore": [
        "\\.vscode",
        "\\.git",
        "firmwareupdates",
        "\\.DS_Store"
    ],
    "generatedFiles": {
        "extensionsToInclude": [
            ""
        ],
        "path": ""
    }
}